xmipp2/__init__.py
xmipp2/bibtex.py
xmipp2/constants.py
xmipp2/protocols.conf
xmipp2/wizards.py
xmipp2/convert/__init__.py
xmipp2/convert/convert.py
xmipp2/protocols/__init__.py
xmipp2/protocols/protocol_mltomo.py
xmipp2/tests/__init__.py
xmipp2/tests/test_protocols_xmipp2.py
xmipp2/viewers/__init__.py
xmipp2/viewers/viewer.py
xmipp2/viewers/viewer_MlTomo.py
scipion_em_xmipp2-3.0.1.dist-info/LICENSE
scipion_em_xmipp2-3.0.1.dist-info/METADATA
scipion_em_xmipp2-3.0.1.dist-info/WHEEL
scipion_em_xmipp2-3.0.1.dist-info/entry_points.txt
scipion_em_xmipp2-3.0.1.dist-info/top_level.txt
scipion_em_xmipp2-3.0.1.dist-info/RECORD
