Metadata-Version: 2.1
Name: scipion-em-xmipp2
Version: 3.0.1
Summary: xmipp2 ready to use in scipion.
Home-page: https://github.com/I2PC/scipion-em-xmipp2.git
Author: I2PC
Author-email: scipion@cnb.csic.es
License: UNKNOWN
Keywords: scipion cryoem imageprocessing scipion-3.0
Platform: UNKNOWN
Requires-Dist: scipion-em-tomo
